{
    "abusive": {
        "buffs": [
            "-15% Stun Resist",
            "-15% Blight Resist",
            "-15% Bleed Resist",
            "-15% Disease Resist",
            "-15% Debuff Resist",
            "-15% Move Resist",
            "-15% Trap Disarm Chance",
            "-10% MAX HP",
            "-5 ACC",
            "+20% DMG",
            "-15 DODGE"
        ],
        "dialogue": "-10% MAX HP, -5 ACC, +20% DMG, -15 DODGE",
        "id": "abusive",
        "name": "Abusive",
        "overstress_type": "affliction"
    },
    "courageous": {
        "buffs": [
            "+25% Stun Resist",
            "+25% Blight Resist",
            "+25% Bleed Resist",
            "+25% Disease Resist",
            "+25% Debuff Resist",
            "+25% Move Resist",
            "-33% Stress if Virtued",
            "+2 SPD if Virtued"
        ],
        "dialogue": "-25% stress damage to companions",
        "message": "-33% Stress, +2 SPD, 25% chance to relieve the party of 4 stress at the beginning of each turn.",
        "id": "courageous",
        "name": "Courageous",
        "overstress_type": "virtue"
    },
    "fearful": {
        "buffs": [
            "-15% Stun Resist",
            "-15% Blight Resist",
            "-15% Bleed Resist",
            "-15% Disease Resist",
            "-15% Debuff Resist",
            "-15% Move Resist",
            "-15% Trap Disarm Chance",
            "-10% MAX HP",
            "-25% DMG",
            "+10 DODGE",
            "+2 SPD"
        ],
        "dialogue": "-10% MAX HP, -25% DMG, +10 DODGE, +2 SPD",
        "id": "fearful",
        "name": "Fearful",
        "overstress_type": "affliction"
    },
    "focused": {
        "buffs": [
            "+25% Stun Resist",
            "+25% Blight Resist",
            "+25% Bleed Resist",
            "+25% Disease Resist",
            "+25% Debuff Resist",
            "+25% Move Resist",
            "+10 ACC if Virtued",
            "+10% CRT if Virtued"
        ],
        "dialogue": "+10 ACC, +10% CRIT",
        "message": "+10 ACC, +10% CRIT, 25% chance to buff another party member for +10 ACC and +10% CRIT at the beginning of each turn.",
        "id": "focused",
        "name": "Focused",
        "overstress_type": "virtue"
    },
    "hopeless": {
        "buffs": [
            "-15% Stun Resist",
            "-15% Blight Resist",
            "-15% Bleed Resist",
            "-15% Disease Resist",
            "-15% Debuff Resist",
            "-15% Move Resist",
            "-15% Trap Disarm Chance",
            "-10% MAX HP",
            "-5 ACC",
            "-5 DODGE",
            "-3 SPD"
        ],
        "dialogue": "-10% MAX HP, -5 ACC, -5 DODGE, -3 SPD",
        "id": "depressed",
        "name": "Hopeless",
        "overstress_type": "affliction"
    },
    "irrational": {
        "buffs": [
            "-15% Stun Resist",
            "-15% Blight Resist",
            "-15% Bleed Resist",
            "-15% Disease Resist",
            "-15% Debuff Resist",
            "-15% Move Resist",
            "-15% Trap Disarm Chance",
            "-10% MAX HP",
            "-5 ACC",
            "-10% DMG",
            "-5 DODGE",
            "+2 SPD"
        ],
        "dialogue": "-10% MAX HP, -5 ACC, -10% DMG, -5 DODGE, +2 SPD",
        "id": "irrational",
        "name": "Irrational",
        "overstress_type": "affliction"
    },
    "masochistic": {
        "buffs": [
            "-15% Stun Resist",
            "-15% Blight Resist",
            "-15% Bleed Resist",
            "-15% Disease Resist",
            "-15% Debuff Resist",
            "-15% Move Resist",
            "-15% Trap Disarm Chance",
            "-10% MAX HP",
            "-15 DODGE"
        ],
        "dialogue": "-10% MAX HP, -15 DODGE",
        "id": "masochistic",
        "name": "Masochistic",
        "overstress_type": "affliction"
    },
    "paranoid": {
        "buffs": [
            "-15% Stun Resist",
            "-15% Blight Resist",
            "-15% Bleed Resist",
            "-15% Disease Resist",
            "-15% Debuff Resist",
            "-15% Move Resist",
            "-15% Trap Disarm Chance",
            "-10% MAX HP",
            "-25% DMG",
            "+10 DODGE",
            "+2 SPD"
        ],
        "dialogue": "-10% MAX HP, -25% DMG, +10 DODGE, +2 SPD",
        "id": "paranoid",
        "name": "Paranoid",
        "overstress_type": "affliction"
    },
    "powerful": {
        "buffs": [
            "+25% Stun Resist",
            "+25% Blight Resist",
            "+25% Bleed Resist",
            "+25% Disease Resist",
            "+25% Debuff Resist",
            "+25% Move Resist",
            "+25% DMG if Virtued"
        ],
        "dialogue": "+25% DMG",
        "message": "+25% DMG, 25% chance to buff the party members for +15% DMG",
        "id": "powerful",
        "name": "Powerful",
        "overstress_type": "virtue"
    },
    "selfish": {
        "buffs": [
            "-15% Stun Resist",
            "-15% Blight Resist",
            "-15% Bleed Resist",
            "-15% Disease Resist",
            "-15% Debuff Resist",
            "-15% Move Resist",
            "-15% Trap Disarm Chance",
            "-10% MAX HP",
            "-5 ACC",
            "-10% DMG",
            "+5 DODGE"
        ],
        "dialogue": "-10% MAX HP, -5 ACC, -10% DMG, +5 DODGE",
        "id": "selfish",
        "name": "Selfish",
        "overstress_type": "affliction"
    },
    "stalwart": {
        "buffs": [
            "+25% Stun Resist",
            "+25% Blight Resist",
            "+25% Bleed Resist",
            "+25% Disease Resist",
            "+25% Debuff Resist",
            "+25% Move Resist",
            "+15% PROT if Virtued",
            "+8% Death Blow Resist if Virtued"
        ],
        "dialogue": "+15% PROT, +8% Death Blow Resist",
        "message": "+15% PROT, +8% Death Blow Resist, 25% chance to stress heal self for 15 at the start of each turn.",
        "id": "stalwart",
        "name": "Stalwart",
        "overstress_type": "virtue"
    },
    "vigorous": {
        "buffs": [
            "+25% Stun Resist",
            "+25% Blight Resist",
            "+25% Bleed Resist",
            "+25% Disease Resist",
            "+25% Debuff Resist",
            "+25% Move Resist",
            "+4 SPD if Virtued",
            "+10 DODGE if Virtued"
        ],
        "dialogue": "+5 SPD, Increased Blight, Bleed, Disease resist",
        "message": "+4 SPD, +10 DODGE",
        "id": "vigorous",
        "name": "Vigorous",
        "overstress_type": "virtue"
    }
}
